README.md
setup.cfg
setup.py
distributions/Binomialdistribution.py
distributions/Gaussiandistribution.py
distributions/Generaldistribution.py
distributions/__init__.py
oop_style_general_distributions.egg-info/PKG-INFO
oop_style_general_distributions.egg-info/SOURCES.txt
oop_style_general_distributions.egg-info/dependency_links.txt
oop_style_general_distributions.egg-info/not-zip-safe
oop_style_general_distributions.egg-info/top_level.txt