Metadata-Version: 1.0
Name: oop-style-general-distributions
Version: 0.1
Summary: Gaussian distributions
Home-page: UNKNOWN
Author: Bidila Timotei
Author-email: bidila.timotei@gmail.com
License: UNKNOWN
Platform: UNKNOWN
